q2label/__init__.py
q2label/datalake.py
q2label/local.py
q2label/target.py
q2label/utils.py
q2label-0.0.3.dist-info/LICENSE
q2label-0.0.3.dist-info/METADATA
q2label-0.0.3.dist-info/WHEEL
q2label-0.0.3.dist-info/top_level.txt
q2label-0.0.3.dist-info/RECORD
